tmconfpy/__init__.py
tmconfpy/__main__.py
tmconfpy/apiserver.py
tmconfpy/cli.py
tmconfpy/parser.py
tmconfpy-1.1.0.dist-info/LICENSE
tmconfpy-1.1.0.dist-info/METADATA
tmconfpy-1.1.0.dist-info/WHEEL
tmconfpy-1.1.0.dist-info/entry_points.txt
tmconfpy-1.1.0.dist-info/RECORD
