Metadata-Version: 2.1
Name: tmconfpy
Version: 1.1.0
Summary: A Python library to serialize F5 BIG-IP configuration files to a python dict or JSON.
Home-page: https://github.com/simonkowallik/tmconfpy
Keywords: F5,DevOps,Security
Author: Simon Kowallik
Author-email: sk-github@simonkowallik.com
Requires-Python: >=3.10,<4.0
Classifier: Development Status :: 5 - Production/Stable
Classifier: Intended Audience :: Developers
Classifier: Intended Audience :: Information Technology
Classifier: Intended Audience :: System Administrators
Classifier: Natural Language :: English
Classifier: Operating System :: OS Independent
Classifier: Programming Language :: Python
Classifier: Programming Language :: Python :: 3
Classifier: Programming Language :: Python :: 3.10
Classifier: Programming Language :: Python :: 3.11
Classifier: Programming Language :: Python :: 3.12
Classifier: Programming Language :: Python :: 3.9
Classifier: Topic :: Internet
Classifier: Topic :: Security
Classifier: Topic :: Software Development
Classifier: Topic :: Software Development :: Libraries
Classifier: Topic :: Software Development :: Libraries :: Python Modules
Classifier: Topic :: System
Classifier: Topic :: System :: Installation/Setup
Classifier: Topic :: System :: Networking
Classifier: Topic :: System :: Systems Administration
Provides-Extra: apiserver
Requires-Dist: fastapi (>=0.111.0,<0.112.0) ; extra == "apiserver"
Requires-Dist: python-multipart (>=0.0.9,<0.0.10) ; extra == "apiserver"
Requires-Dist: uvicorn (>=0.30.1,<0.31.0) ; extra == "apiserver"
Project-URL: Documentation, https://github.com/simonkowallik/tmconfpy
Project-URL: Repository, https://github.com/simonkowallik/tmconfpy
